[
  {"x": 4, "y": 2, "type": "house_red", "rotation": 90},
  {"x": 4, "y": 3, "type": "house_red", "rotation": 90},
  {"x": 4, "y": 4, "type": "house_red", "rotation": 90},
  {"x": 3, "y": 1, "type": "street", "rotation": 0},
  {"x": 4, "y": 1, "type": "street", "rotation": 0},
  {"x": 5, "y": 1, "type": "street", "rotation": 0},
  {"x": 6, "y": 1, "type": "street", "rotation": 0},
  {"x": 7, "y": 1, "type": "street", "rotation": 0},
  {"x": 8, "y": 1, "type": "street", "rotation": 0},
  {"x": 9, "y": 1, "type": "street", "rotation": 0},
  {"x": 10,"y": 1, "type": "street", "rotation": 0},
  {"x": 11,"y": 1, "type": "street", "rotation": 0},
  {"x": 12,"y": 1, "type": "street", "rotation": 0},
  {"x": 3, "y": 2, "type": "street", "rotation": 0},
  {"x": 3, "y": 3, "type": "street", "rotation": 0},
  {"x": 3, "y": 4, "type": "street", "rotation": 0},
  {"x": 3, "y": 5, "type": "street", "rotation": 0},
  {"x": 3, "y": 6, "type": "street", "rotation": 0},
  {"x": 3, "y": 7, "type": "street", "rotation": 0},
  {"x": 3, "y": 8, "type": "street", "rotation": 0},
  {"x": 2, "y": 6, "type": "street", "rotation": 0},
  {"x": 1, "y": 6, "type": "street", "rotation": 0},
  {"x": 1, "y": 7, "type": "street", "rotation": 0},
  {"x": 1, "y": 8, "type": "street", "rotation": 0},
  {"x": 2, "y": 8, "type": "street", "rotation": 0},
  {"x": 7, "y": 2, "type": "street", "rotation": 0},
  {"x": 7, "y": 3, "type": "street", "rotation": 0},
  {"x": 7, "y": 4, "type": "street", "rotation": 0},
  {"x": 7, "y": 5, "type": "street", "rotation": 0},
  {"x": 7, "y": 6, "type": "street", "rotation": 0},
  {"x": 7, "y": 7, "type": "street", "rotation": 0},
  {"x": 7, "y": 8, "type": "street", "rotation": 0},
  {"x": 4, "y": 8, "type": "street", "rotation": 0},
  {"x": 5, "y": 8, "type": "street", "rotation": 0},
  {"x": 6, "y": 8, "type": "street", "rotation": 0},
  {"x": 7, "y": 8, "type": "street", "rotation": 0},
  {"x": 7, "y": 9, "type": "street", "rotation": 0},
  {"x": 8, "y": 9, "type": "street", "rotation": 0},
  {"x": 9, "y": 9, "type": "street", "rotation": 0},
  {"x": 10,"y": 9, "type": "street", "rotation": 0},
  {"x": 11,"y": 9, "type": "street", "rotation": 0},
  {"x": 11,"y": 8, "type": "street", "rotation": 0},
  {"x": 11,"y": 7, "type": "street", "rotation": 0},
  {"x": 11,"y": 6, "type": "street", "rotation": 0},
  {"x": 11,"y": 5, "type": "street", "rotation": 0},
  {"x": 11,"y": 4, "type": "street", "rotation": 0},
  {"x": 12,"y": 4, "type": "street", "rotation": 0},
  {"x": 10,"y": 4, "type": "street", "rotation": 0},
  {"x": 9, "y": 4, "type": "street", "rotation": 0},
  {"x": 8, "y": 4, "type": "street", "rotation": 0},
  {"x": 8, "y": 6, "type": "street", "rotation": 0},
  {"x": 9, "y": 6, "type": "street", "rotation": 0},
  {"x": 10,"y": 6, "type": "street", "rotation": 0},
  {"x": 4, "y": 5, "type": "street", "rotation": 0},
  {"x": 5, "y": 5, "type": "street", "rotation": 0},
  {"x": 6, "y": 5, "type": "street", "rotation": 0},
  {"x": 9, "y": 10,"type": "street",  "rotation": 0}
]